{
    "data": [
        {
            "firstname": "John",
            "lastname": "Doe",
            "email": "john.doe@example.com",
            "phone": "+1234567890",
            "events_attended": ["Event A", "Event B"],
            "category": "regular",
            "registered_on": "2023-09-20",
            "registered_by": "admin1"
        },
        {
            "firstname": "Jane",
            "lastname": "Smith",
            "email": "jane.smith@example.com",
            "phone": "+1234567891",
            "events_attended": ["Event A", "Event C", "Event D"],
            "category": "vip",
            "registered_on": "2023-09-19",
            "registered_by": "admin2"
        },
        {
            "firstname": "Alice",
            "lastname": "Johnson",
            "email": "alice.johnson@example.com",
            "phone": "+1234567892",
            "events_attended": ["Event B", "Event D"],
            "category": "regular",
            "registered_on": "2023-09-18",
            "registered_by": "admin3"
        },
        {
            "firstname": "Bob",
            "lastname": "Williams",
            "email": "bob.williams@example.com",
            "phone": "+1234567893",
            "events_attended": ["Event A"],
            "category": "vvip",
            "registered_on": "2023-09-17",
            "registered_by": "admin1"
        },
        {
            "firstname": "Charlie",
            "lastname": "Brown",
            "email": "charlie.brown@example.com",
            "phone": "+1234567894",
            "events_attended": ["Event C", "Event D"],
            "category": "vip",
            "registered_on": "2023-09-16",
            "registered_by": "admin2"
        },
        {
            "firstname": "Eve",
            "lastname": "White",
            "email": "eve.white@example.com",
            "phone": "+1234567895",
            "events_attended": ["Event A", "Event B", "Event C"],
            "category": "regular",
            "registered_on": "2023-09-15",
            "registered_by": "admin3"
        },
        {
            "firstname": "Frank",
            "lastname": "Black",
            "email": "frank.black@example.com",
            "phone": "+1234567896",
            "events_attended": ["Event D"],
            "category": "vvip",
            "registered_on": "2023-09-14",
            "registered_by": "admin1"
        },
        {
            "firstname": "Grace",
            "lastname": "Green",
            "email": "grace.green@example.com",
            "phone": "+1234567897",
            "events_attended": ["Event A", "Event D"],
            "category": "vip",
            "registered_on": "2023-09-13",
            "registered_by": "admin2"
        },
        {
            "firstname": "Helen",
            "lastname": "Blue",
            "email": "helen.blue@example.com",
            "phone": "+1234567898",
            "events_attended": ["Event B", "Event C"],
            "category": "regular",
            "registered_on": "2023-09-12",
            "registered_by": "admin3"
        },
        {
            "firstname": "Ivan",
            "lastname": "Gray",
            "email": "ivan.gray@example.com",
            "phone": "+1234567899",
            "events_attended": ["Event A", "Event B"],
            "category": "vvip",
            "registered_on": "2023-09-11",
            "registered_by": "admin1"
        },
        {
            "firstname": "Ivan",
            "lastname": "Gray",
            "email": "ivan.gray@example.com",
            "phone": "+1234567899",
            "events_attended": ["Event A", "Event B"],
            "category": "vvip",
            "registered_on": "2023-09-11",
            "registered_by": "admin1"
        },
        {
            "firstname": "Ivan",
            "lastname": "Gray",
            "email": "ivan.gray@example.com",
            "phone": "+1234567899",
            "events_attended": ["Event A", "Event B"],
            "category": "vvip",
            "registered_on": "2023-09-11",
            "registered_by": "admin1"
        },

        {
            "firstname": "Jacob",
            "lastname": "Silver",
            "email": "jacob.silver@example.com",
            "phone": "+1234567800",
            "events_attended": ["Event B", "Event D"],
            "category": "regular",
            "registered_on": "2023-09-10",
            "registered_by": "admin2"
        },
        {
            "firstname": "Kelly",
            "lastname": "Gold",
            "email": "kelly.gold@example.com",
            "phone": "+1234567801",
            "events_attended": ["Event A", "Event C", "Event D"],
            "category": "vip",
            "registered_on": "2023-09-09",
            "registered_by": "admin3"
        },
        {
            "firstname": "Lucas",
            "lastname": "Bronze",
            "email": "lucas.bronze@example.com",
            "phone": "+1234567802",
            "events_attended": ["Event A", "Event B"],
            "category": "vvip",
            "registered_on": "2023-09-08",
            "registered_by": "admin1"
        },
        {
            "firstname": "Mia",
            "lastname": "Pearl",
            "email": "mia.pearl@example.com",
            "phone": "+1234567803",
            "events_attended": ["Event C", "Event D"],
            "category": "regular",
            "registered_on": "2023-09-07",
            "registered_by": "admin2"
        },
        {
            "firstname": "Nolan",
            "lastname": "Jade",
            "email": "nolan.jade@example.com",
            "phone": "+1234567804",
            "events_attended": ["Event A", "Event D"],
            "category": "vip",
            "registered_on": "2023-09-06",
            "registered_by": "admin3"
        },
        {
            "firstname": "Olivia",
            "lastname": "Ruby",
            "email": "olivia.ruby@example.com",
            "phone": "+1234567805",
            "events_attended": ["Event A", "Event B", "Event C"],
            "category": "vvip",
            "registered_on": "2023-09-05",
            "registered_by": "admin1"
        },
        {
            "firstname": "Patrick",
            "lastname": "Diamond",
            "email": "patrick.diamond@example.com",
            "phone": "+1234567806",
            "events_attended": ["Event B"],
            "category": "regular",
            "registered_on": "2023-09-04",
            "registered_by": "admin2"
        },
        {
            "firstname": "Quincy",
            "lastname": "Amethyst",
            "email": "quincy.amethyst@example.com",
            "phone": "+1234567807",
            "events_attended": ["Event A", "Event D"],
            "category": "vip",
            "registered_on": "2023-09-03",
            "registered_by": "admin3"
        },
        {
            "firstname": "Rachel",
            "lastname": "Emerald",
            "email": "rachel.emerald@example.com",
            "phone": "+1234567808",
            "events_attended": ["Event C", "Event D"],
            "category": "vvip",
            "registered_on": "2023-09-02",
            "registered_by": "admin1"
        },
        {
            "firstname": "Steven",
            "lastname": "Sapphire",
            "email": "steven.sapphire@example.com",
            "phone": "+1234567809",
            "events_attended": ["Event A", "Event B", "Event C"],
            "category": "regular",
            "registered_on": "2023-09-01",
            "registered_by": "admin2"
        }
    ]
}
